square_file_store/__init__.py
square_file_store/configuration.py
square_file_store/data/config.sample.ini
square_file_store/data/config.testing.sample.ini
square_file_store/main.py
square_file_store/messages.py
square_file_store/pydantic_models/__init__.py
square_file_store/pydantic_models/core.py
square_file_store/routes/__init__.py
square_file_store/routes/core.py
square_file_store/utils/__init__.py
square_file_store/utils/helper.py
square_file_store/utils/routes/__init__.py
square_file_store/utils/routes/core.py
square_file_store-2.4.1.dist-info/WHEEL
square_file_store-2.4.1.dist-info/METADATA
square_file_store-2.4.1.dist-info/RECORD
