Metadata-Version: 2.3
Name: square_file_store
Version: 2.4.1
Summary: file storage layer for my personal server.
Keywords: file,storage,fastapi,utilities
Author: Parth Mukesh Mangtani
Author-email: Parth Mukesh Mangtani <thepmsquare@gmail.com>
License: GPLv3
Classifier: Development Status :: 3 - Alpha
Classifier: Intended Audience :: Developers
Classifier: License :: OSI Approved :: GNU General Public License v3 (GPLv3)
Classifier: Programming Language :: Python :: 3
Classifier: Programming Language :: Python :: 3.12
Classifier: Programming Language :: Python :: 3 :: Only
Classifier: Topic :: Utilities
Classifier: Topic :: Internet :: WWW/HTTP :: Dynamic Content
Classifier: Framework :: FastAPI
Requires-Dist: uvicorn>=0.24.0.post1
Requires-Dist: fastapi>=0.104.1
Requires-Dist: python-multipart>=0.0.6
Requires-Dist: pydantic>=2.5.3
Requires-Dist: square-logger>=3.0.0
Requires-Dist: square-database-helper>=2.7.1
Requires-Dist: square-commons>=3.1.0
Requires-Dist: square-database-structure>=2.5.1
Requires-Dist: httpx>=0.27.2
Requires-Dist: pytest>=8.0.0 ; extra == 'all'
Requires-Dist: pytest>=8.0.0 ; extra == 'dev'
Requires-Python: >=3.12
Project-URL: homepage, https://github.com/thepmsquare/square_file_store
Provides-Extra: all
Provides-Extra: dev
